<text>
<p>
<nama> Musmulyadi </nama><br>
<jk> Laki-laki </jk><br>
<posisi> Pemilik Rumah Makan </posisi>

<p>
<nama> Siti Maryam </nama><br>
<jk> Perempuan </jk><br>
<posisi> Koki </posisi>

<p>
<nama> Adriyanto</nama><br>
<jk> Laki-laki </jk><br>
<posisi> Koki </posisi>

<p>
<nama> Arip Budiman </nama><br>
<jk> Laki-laki </jk><br>
<posisi> Koki </posisi>

<p>
<nama> Nuranisa</nama><br>
<jk> Perempuan </jk><br>
<posisi> Koki </posisi>

<p>
<nama> Nani </nama><br>
<jk> Perempuan </jk><br>
<posisi> Pelayan </posisi>



</text>